Leetease/__init__.py
Leetease-0.3.0.dist-info/METADATA
Leetease-0.3.0.dist-info/WHEEL
Leetease-0.3.0.dist-info/top_level.txt
Leetease-0.3.0.dist-info/RECORD
