Metadata-Version: 2.1
Name: Leetease
Version: 0.3.0
Summary: This makes LeetCode Interview programs easy
Author: SaatwikCodz
